deepbookpy/__init__.py
deepbookpy/custom_types/__init__.py
deepbookpy/custom_types/serialization_types.py
deepbookpy/deepbook_client.py
deepbookpy/transactions/balance_manager.py
deepbookpy/transactions/deepbook.py
deepbookpy/transactions/deepbook_admin.py
deepbookpy/transactions/flash_loans.py
deepbookpy/transactions/governance.py
deepbookpy/utils/coin.py
deepbookpy/utils/config.py
deepbookpy/utils/constants.py
deepbookpy/utils/normalizer.py
deepbookpy/version.py
deepbookpy-0.7.1.dist-info/METADATA
deepbookpy-0.7.1.dist-info/WHEEL
deepbookpy-0.7.1.dist-info/licenses/LICENSE
deepbookpy-0.7.1.dist-info/RECORD
