Metadata-Version: 2.4
Name: deepbookpy
Version: 0.7.1
Summary: Sui Deepbook Python SDK
License: Apache-2.0
License-File: LICENSE
Keywords: sui deepbook python sdk,deepbook,blockchain
Author: Andrei
Author-email: andreid.dev@gmail.com
Requires-Python: >=3.10
Classifier: License :: OSI Approved :: Apache Software License
Classifier: Programming Language :: Python :: 3
Classifier: Programming Language :: Python :: 3.10
Classifier: Programming Language :: Python :: 3.11
Classifier: Programming Language :: Python :: 3.12
Classifier: Programming Language :: Python :: 3.13
Classifier: Programming Language :: Python :: 3.14
Provides-Extra: docs
Requires-Dist: pysui (>=0.83.0,<0.84.0)
Project-URL: Documentation, https://deepbookpy.readthedocs.io
Project-URL: Repository, https://github.com/andreidev1/deepbookpy
Project-URL: changelog, https://github.com/andreidev1/deepbookpy/blob/main/CHANGELOG.md
Project-URL: issues, https://github.com/andreidev1/deepbookpy/issues
